{
    "type": "movies",
    "total": 309771,
    "movies": [
        {
            "cat": "动作,冒险,科幻",
            "dir": "蒂姆·米勒",
            "dur": 127,
            "enm": "Terminator: Dark Fate",
            "fra": "美国",
            "frt": "2019-11-01",
            "globalReleased": true,
            "id": 247730,
            "img": "http://p0.meituan.net/w.h/movie/b932f7f678a3e28763b3b281b3e120ef13622509.jpg",
            "movieType": 0,
            "nm": "终结者：黑暗命运",
            "onlinePlay": false,
            "pubDesc": "2019-11-01大陆上映",
            "rt": "2019-11-01",
            "sc": 8.6,
            "show": "",
            "showst": 2,
            "star": "阿诺德·施瓦辛格,琳达·汉密尔顿,麦肯兹·戴维斯",
            "type": 0,
            "ver": "IMAX 2D/中国巨幕2D",
            "vodPlay": false,
            "wish": 149017,
            "wishst": 0,
            "version": "v2d imax"
        },
        {
            "cat": "动作,冒险,科幻",
            "dir": "詹姆斯·卡梅隆",
            "dur": 0,
            "enm": "Avatar 2",
            "fra": "美国",
            "frt": "2020-12-18",
            "globalReleased": false,
            "id": 78461,
            "img": "http://p0.meituan.net/w.h/movie/1c37b971999a263a76f1e76598fc8397153328.jpg",
            "movieType": 0,
            "nm": "阿凡达2",
            "onlinePlay": false,
            "pubDesc": "2020-12-18美国上映",
            "rt": "2020-12-18",
            "sc": 0,
            "show": "",
            "showst": 1,
            "star": "萨姆·沃辛顿,佐伊·索尔达娜,西格妮·韦弗",
            "type": 0,
            "ver": "IMAX 3D/3D",
            "vodPlay": false,
            "wish": 403622,
            "wishst": 0,
            "version": "v3d imax"
        },
        {
            "cat": "动作",
            "dir": "林德禄",
            "dur": 110,
            "enm": "Littoral Confrontation",
            "globalReleased": false,
            "id": 1292157,
            "img": "http://p1.meituan.net/w.h/moviemachine/20f77875a23f40a705ae23d2982b69bf627441.jpg",
            "movieType": 0,
            "nm": "濒海交锋",
            "onlinePlay": false,
            "pubDesc": "2020大陆上映",
            "rt": "2020",
            "sc": 0,
            "show": "",
            "showst": 1,
            "star": "徐佳,丁海峰,韩飞行",
            "time": "2020",
            "type": 0,
            "ver": "3D",
            "vodPlay": false,
            "wish": 436,
            "wishst": 0,
            "version": "v3d"
        },
        {
            "cat": "剧情,爱情,青春",
            "dir": "宋文",
            "dur": 0,
            "enm": "The Enigma Of Arrival",
            "fra": "韩国",
            "frt": "2018-10-05",
            "globalReleased": false,
            "id": 342485,
            "img": "http://p1.meituan.net/w.h/moviemachine/1c5f6661ceb721d741d5335cf2ecfce2257594.jpg",
            "movieType": 0,
            "nm": "抵达之谜",
            "onlinePlay": false,
            "pubDesc": "2020大陆上映",
            "rt": "2020",
            "sc": 0,
            "show": "",
            "showst": 1,
            "star": "李现,董博睿,顾璇",
            "time": "2020",
            "type": 0,
            "ver": "2D",
            "vodPlay": false,
            "wish": 37398,
            "wishst": 0,
            "version": ""
        },
        {
            "cat": "喜剧,爱情,动作",
            "dir": "刘仪伟",
            "dur": 106,
            "enm": "At Last",
            "globalReleased": false,
            "id": 1286060,
            "img": "http://p0.meituan.net/w.h/movie/077f41ce44d059a01288e0d7bf704f9f1642095.jpg",
            "movieType": 0,
            "nm": "玩命三日",
            "onlinePlay": false,
            "pubDesc": "2020大陆上映",
            "rt": "2020",
            "sc": 0,
            "show": "",
            "showst": 1,
            "star": "张嘉译,闫妮,姜妍",
            "time": "2020",
            "type": 0,
            "ver": "2D",
            "vodPlay": false,
            "wish": 33358,
            "wishst": 0,
            "version": ""
        },
        {
            "cat": "动作",
            "dir": "Boyapati Srinu",
            "dur": 152,
            "enm": "Vinaya Vidheya Rama",
            "fra": "加拿大,爱尔兰,科威特,美国,澳大利亚,英国,印度,新西兰",
            "frt": "2019-01-10,2019-01-10,2019-01-10,2019-01-10,2019-01-11,2019-01-11,2019-01-11,2019-01-11",
            "ftime": ",,,,,,,",
            "globalReleased": true,
            "id": 1251260,
            "img": "http://p0.meituan.net/w.h/movie/b36ca7cc25c1a48211a4dff9bb27a713142447.jpg",
            "movieType": 0,
            "nm": "黄沙战神",
            "onlinePlay": false,
            "pubDesc": "2019-01-10加拿大上映",
            "rt": "2019-01-10",
            "sc": 0,
            "show": "",
            "showst": 2,
            "star": "Kiara Advani,哈里什·乌达曼,拉姆·查兰·特哈",
            "type": 0,
            "vodPlay": false,
            "wish": 223,
            "wishst": 0
        },
        {
            "cat": "奇幻,冒险,爱情",
            "dir": "丁亮,林永长",
            "dur": 0,
            "enm": "Realm of Terracotta",
            "globalReleased": false,
            "id": 1250950,
            "img": "http://p0.meituan.net/w.h/moviemachine/56714bf223954991175f333864454127651389.jpg",
            "movieType": 0,
            "nm": "俑之城",
            "onlinePlay": false,
            "pubDesc": "2020大陆上映",
            "rt": "2020",
            "sc": 0,
            "show": "",
            "showst": 1,
            "star": "谭笑,周子瑜,刘沛",
            "time": "2020",
            "type": 0,
            "ver": "3D",
            "vodPlay": false,
            "wish": 6876,
            "wishst": 0,
            "version": "v3d"
        },
        {
            "cat": "动作,科幻,奇幻,冒险",
            "dir": "乔斯·韦登",
            "dur": 142,
            "enm": "The Avengers",
            "fra": "美国,澳大利亚,比利时,法国,意大利,荷兰,新西兰,菲律宾,葡萄牙,中国台湾,阿根廷,奥地利,玻利维亚,智利,德国,丹麦,多明尼加,英国,希腊,中国香港,匈牙利,爱尔兰,韩国,马来西亚,秘鲁,南非,巴西,哥伦比亚,哥斯达黎加,厄瓜多尔,西班牙,芬兰,危地马拉,印度,冰岛,墨西哥,挪威,巴拿马,巴拉圭,瑞典,乌拉圭,委内瑞拉,越南,美国,保加利亚,拉脱维亚,新加坡,泰国,埃及,塞尔维亚,阿联酋,巴林,捷克,克罗地亚,科威特,哈萨克斯坦,黎巴嫩,塞尔维亚,俄罗斯,斯洛文尼亚,斯洛伐克,乌克兰,加拿大,爱沙尼亚,加纳,印度尼西亚,立陶宛,尼日利亚,罗马尼亚,土耳其,美国,美国,亚美尼亚,以色列,Republic of North Macedonia,巴基斯坦,波兰,柬埔寨,格鲁吉亚,孟加拉国,日本",
            "frt": "2012-04-11,2012-04-25,2012-04-25,2012-04-25,2012-04-25,2012-04-25,2012-04-25,2012-04-25,2012-04-25,2012-04-25,2012-04-26,2012-04-26,2012-04-26,2012-04-26,2012-04-26,2012-04-26,2012-04-26,2012-04-26,2012-04-26,2012-04-26,2012-04-26,2012-04-26,2012-04-26,2012-04-26,2012-04-26,2012-04-26,2012-04-27,2012-04-27,2012-04-27,2012-04-27,2012-04-27,2012-04-27,2012-04-27,2012-04-27,2012-04-27,2012-04-27,2012-04-27,2012-04-27,2012-04-27,2012-04-27,2012-04-27,2012-04-27,2012-04-27,2012-04-28,2012-05-01,2012-05-01,2012-05-01,2012-05-01,2012-05-02,2012-05-02,2012-05-03,2012-05-03,2012-05-03,2012-05-03,2012-05-03,2012-05-03,2012-05-03,2012-05-03,2012-05-03,2012-05-03,2012-05-03,2012-05-03,2012-05-04,2012-05-04,2012-05-04,2012-05-04,2012-05-04,2012-05-04,2012-05-04,2012-05-04,2012-05-04,2012-05-04,2012-05-10,2012-05-10,2012-05-11,2012-05-11,2012-05-11,2012-05-17,2012-05-31,2012-08-03,2012-08-14",
            "ftime": ",,,,,,,,,,,,,,,,,,,,,,,,,,,,,,,,,,,,,,,,,,,,,,,,,,,,,,,,,,,,,,,,,,,,,,,,,,,,,,,,",
            "globalReleased": true,
            "id": 262,
            "img": "http://p0.meituan.net/w.h/movie/4286d8614c24fd6310266847c0314613419936.jpg",
            "movieType": 0,
            "nm": "复仇者联盟",
            "onlinePlay": false,
            "pubDesc": "2012-05-05大陆上映",
            "rt": "2012-05-05",
            "sc": 8.7,
            "show": "",
            "showst": 2,
            "star": "小罗伯特·唐尼,克里斯·埃文斯,马克·鲁法洛",
            "type": 0,
            "ver": "IMAX 3D/3D",
            "vodPlay": false,
            "wish": 399,
            "wishst": 0,
            "version": "v3d imax"
        },
        {
            "cat": "剧情,喜剧,犯罪",
            "dir": "饶晓志",
            "dur": 108,
            "enm": "A Cool Fish",
            "fra": "美国,中国香港",
            "frt": "2018-11-16,2018-11-22",
            "globalReleased": true,
            "id": 1208282,
            "img": "http://p0.meituan.net/w.h/movie/db233a95c927420707ec0ed47d29f21d321171.jpg",
            "movieType": 0,
            "nm": "无名之辈",
            "onlinePlay": false,
            "pubDesc": "2018-11-16大陆上映",
            "rt": "2018-11-16",
            "sc": 9,
            "show": "",
            "showst": 2,
            "star": "陈建斌,任素汐,潘斌龙",
            "type": 0,
            "ver": "2D",
            "vodPlay": false,
            "wish": 15666,
            "wishst": 0,
            "version": ""
        },
        {
            "cat": "动画",
            "dir": "长井龙雪",
            "dur": 112,
            "enm": "空の青さを知る人よ",
            "fra": "西班牙,日本,新加坡,越南,菲律宾,印度尼西亚,荷兰,中国台湾,意大利",
            "frt": "2019-10-09,2019-10-11,2019-12-12,2020-01-10,2020-02-12,2020-03-11,,2020-04-17,2020-05-11",
            "ftime": ",,,,,,2020-04,,",
            "globalReleased": true,
            "id": 1278417,
            "img": "http://p0.meituan.net/w.h/movie/59b7973b6724f9833e8230dafd1a9cbe281004.jpg",
            "movieType": 0,
            "nm": "知晓天空之蓝的人啊",
            "onlinePlay": false,
            "pubDesc": "2019-10-09西班牙上映",
            "rt": "2019-10-09",
            "sc": 7.2,
            "show": "",
            "showst": 2,
            "star": "吉沢亮,吉冈里帆,松平健",
            "type": 0,
            "vodPlay": false,
            "wish": 805,
            "wishst": 0
        },
        {
            "cat": "爱情,喜剧",
            "dir": "周申,刘露",
            "dur": 111,
            "enm": "Almost a Comedy",
            "globalReleased": true,
            "id": 1228869,
            "img": "http://p0.meituan.net/w.h/movie/9064b787a533d85fa2d2f8ad486351861051512.jpg",
            "movieType": 0,
            "nm": "半个喜剧",
            "onlinePlay": false,
            "pubDesc": "2019-12-20大陆上映",
            "rt": "2019-12-20",
            "sc": 9,
            "show": "",
            "showst": 2,
            "star": "任素汐,吴昱翰,刘迅",
            "type": 0,
            "ver": "2D",
            "vodPlay": false,
            "wish": 34803,
            "wishst": 0,
            "version": ""
        },
        {
            "cat": "综艺,真人秀",
            "dir": "吴彤",
            "dur": 108,
            "enm": "Trump Card season V",
            "globalReleased": true,
            "id": 1302449,
            "img": "http://p0.meituan.net/w.h/moviemachine/edaa61f41e9711373c145334a2d50012639465.jpg",
            "movieType": 2,
            "nm": "王牌对王牌 第五季",
            "onlinePlay": false,
            "pubDesc": "2020-02-21大陆首播",
            "rt": "2020-02-21",
            "sc": 0,
            "show": "",
            "showst": 0,
            "star": "沈涛,沈腾,贾玲",
            "type": 0,
            "ver": "2D",
            "vodPlay": false,
            "wish": 39,
            "wishst": 0,
            "version": ""
        },
        {
            "cat": "喜剧,动作,奇幻,冒险",
            "dir": "乔阿吉姆·罗恩尼",
            "dur": 120,
            "enm": "Untitled Pirates of the Caribbean Project",
            "fra": "美国",
            "ftime": "2021",
            "globalReleased": false,
            "id": 341206,
            "img": "http://p0.meituan.net/w.h/movie/cf2631288e8239376e2f300cab4dc0ab93223.jpg",
            "movieType": 0,
            "nm": "加勒比海盗6：四海之怒",
            "onlinePlay": false,
            "pubDesc": "2021美国上映",
            "rt": "2021",
            "sc": 0,
            "show": "",
            "showst": 1,
            "star": "比尔·奈伊,约翰尼·德普,奥兰多·布鲁姆",
            "type": 0,
            "ver": "2D",
            "vodPlay": false,
            "wish": 13514,
            "wishst": 0,
            "version": ""
        },
        {
            "cat": "动画,短片",
            "dir": "石立太一,藤田春香,小川太一",
            "dur": 34,
            "enm": "ヴァイオレット・エヴァーガーデン Extra Episode",
            "fra": "日本",
            "frt": "2018-07-04",
            "globalReleased": true,
            "id": 1240025,
            "img": "http://p0.meituan.net/w.h/movie/bf9e9ec82dddddce7328321b940b397079910.jpg",
            "movieType": 0,
            "nm": "紫罗兰永恒花园",
            "onlinePlay": false,
            "pubDesc": "2018-07-04日本上映",
            "rt": "2018-07-04",
            "sc": 8.7,
            "show": "",
            "showst": 2,
            "star": "石川由依,子安武人,日笠阳子",
            "type": 0,
            "vodPlay": false,
            "wish": 230,
            "wishst": 0
        },
        {
            "cat": "电视剧,剧情",
            "dir": "吕赢",
            "dur": 45,
            "enm": "The Oath of Love",
            "globalReleased": false,
            "id": 1262522,
            "img": "http://p0.meituan.net/w.h/moviemachine/501e647e5fd4ef92d6ce40fb559831123262373.jpg",
            "movieType": 1,
            "nm": "余生，请多指教",
            "onlinePlay": false,
            "pubDesc": "2020大陆首播",
            "rt": "2020",
            "sc": 0,
            "show": "",
            "showst": 0,
            "star": "杨紫,肖战,翟子路",
            "time": "2020",
            "type": 0,
            "ver": "2D",
            "vodPlay": false,
            "wish": 3385,
            "wishst": 0,
            "version": ""
        },
        {
            "cat": "电视剧,动画",
            "dir": "丁亮,李宁",
            "dur": 12,
            "enm": "Boonie Bears:The Adventurs 2",
            "globalReleased": true,
            "id": 1247379,
            "img": "http://p0.meituan.net/w.h/movie/60381562a80c3705b9642d309d84e610277801.jpg",
            "movieType": 1,
            "nm": "熊出没之探险日记2",
            "onlinePlay": false,
            "pubDesc": "2019-02-11大陆首播",
            "rt": "2019-02-11",
            "sc": 9.4,
            "show": "",
            "showst": 0,
            "star": "周子瑜,张秉君,谭笑",
            "type": 0,
            "ver": "2D",
            "vodPlay": false,
            "wish": 1040,
            "wishst": 0,
            "version": ""
        },
        {
            "cat": "奇幻,冒险",
            "dir": "大卫·叶茨",
            "dur": 130,
            "enm": "Harry Potter and the Deathly Hallows: Part 2",
            "fra": "美国",
            "frt": "2011-07-15",
            "globalReleased": true,
            "id": 916,
            "img": "http://p1.meituan.net/w.h/movie/bb0eca029cd25329776a4549b3fbe262924727.jpg",
            "movieType": 0,
            "nm": "哈利·波特与死亡圣器（下）",
            "onlinePlay": false,
            "pubDesc": "2011-08-04大陆上映",
            "rt": "2011-08-04",
            "sc": 9,
            "show": "",
            "showst": 2,
            "star": "丹尼尔·雷德克里夫,鲁伯特·格林特,艾玛·沃特森",
            "type": 0,
            "ver": "IMAX 3D/3D",
            "vodPlay": false,
            "wish": 21,
            "wishst": 0,
            "version": "v3d imax"
        },
        {
            "cat": "爱情",
            "dir": "惠楷栋,孙兆一,王成欣",
            "dur": 45,
            "enm": "Winter Gegonia",
            "globalReleased": true,
            "id": 1234405,
            "img": "http://p1.meituan.net/w.h/moviemachine/6f46c95a4544469cb4dc13fbef01a264319516.jpg",
            "movieType": 5,
            "nm": "鬓边不是海棠红",
            "onlinePlay": false,
            "pubDesc": "2020-03-20大陆首播",
            "rt": "2020-03-20",
            "sc": 7.9,
            "show": "",
            "showst": 0,
            "star": "黄晓明,尹正,佘诗曼",
            "type": 0,
            "ver": "2D",
            "vodPlay": false,
            "wish": 107,
            "wishst": 0,
            "version": ""
        },
        {
            "cat": "剧情,历史,灾难",
            "dir": "冯小刚",
            "dur": 139,
            "enm": "Aftershock",
            "fra": "澳大利亚",
            "frt": "2010-07-22",
            "globalReleased": true,
            "id": 180,
            "img": "http://p0.meituan.net/w.h/movie/1f4bc49ed6c5a3ba23a93ecd68b73da1362146.jpg",
            "movieType": 0,
            "nm": "唐山大地震",
            "onlinePlay": false,
            "pubDesc": "2010-07-22大陆上映",
            "rt": "2010-07-22",
            "sc": 8.2,
            "show": "",
            "showst": 2,
            "star": "徐帆,张静初,李晨",
            "type": 0,
            "ver": "IMAX 2D/2D",
            "vodPlay": false,
            "wish": 60,
            "wishst": 0,
            "version": "v2d imax"
        },
        {
            "cat": "剧情,青春,悬疑",
            "dir": "张伟克",
            "dur": 45,
            "enm": "My roommate is a detective",
            "globalReleased": true,
            "id": 1281573,
            "img": "http://p0.meituan.net/w.h/moviemachine/76da8ae0549ef88df6436dd244156a7b705295.jpg",
            "movieType": 5,
            "nm": "民国奇探",
            "onlinePlay": false,
            "pubDesc": "2020-03-24大陆首播",
            "rt": "2020-03-24",
            "sc": 7.6,
            "show": "",
            "showst": 0,
            "star": "胡一天,张云龙,肖燕",
            "type": 0,
            "ver": "2D",
            "vodPlay": false,
            "wish": 52,
            "wishst": 0,
            "version": ""
        }
    ],
    "keyword": "a",
    "allowRefund": true,
    "endorse": true,
    "snack": true,
    "vipTag": true
}